{"name":"build-javascript","namedChunkGroups":{"app":{"name":"app","assets":[{"name":"webpack-runtime-e6017f85c6a61014f28d.js","size":3677},{"name":"framework-3220af8661d4f7628f82.js","size":141427},{"name":"styles.e056b47e45ae99f4c16e.css","size":6365},{"name":"app-2f44fc91894654af818b.js","size":61211}],"filteredAssets":0,"assetsSize":212680,"filteredAuxiliaryAssets":3,"auxiliaryAssetsSize":590665},"component---src-pages-404-tsx":{"name":"component---src-pages-404-tsx","assets":[{"name":"component---src-pages-404-tsx-44d232805bacbb66e702.js","size":604}],"filteredAssets":0,"assetsSize":604,"filteredAuxiliaryAssets":1,"auxiliaryAssetsSize":942},"component---src-pages-index-tsx":{"name":"component---src-pages-index-tsx","assets":[{"name":"component---src-pages-index-tsx-3e270359f38c18599b32.js","size":17008}],"filteredAssets":0,"assetsSize":17008,"filteredAuxiliaryAssets":1,"auxiliaryAssetsSize":80772}},"assetsByChunkName":{"app":["webpack-runtime-e6017f85c6a61014f28d.js","framework-3220af8661d4f7628f82.js","styles.e056b47e45ae99f4c16e.css","app-2f44fc91894654af818b.js"],"component---src-pages-404-tsx":["component---src-pages-404-tsx-44d232805bacbb66e702.js"],"component---src-pages-index-tsx":["component---src-pages-index-tsx-3e270359f38c18599b32.js"]},"childAssetsByChunkName":{}}